{
  "version": 1,
  "groups": [
    {
      "id": "apps",
      "label": {
        "hu": "Alkalmazásprofilok",
        "en": "Application profiles"
      },
      "description": {
        "hu": "Böngészők, kommunikációs appok és fontos desktop alkalmazások profiljai.",
        "en": "Profiles of browsers, communication apps, and important desktop applications."
      },
      "default_expanded": true,
      "items": [
        {
          "id": "librewolf_profile",
          "label": {
            "hu": "LibreWolf profil",
            "en": "LibreWolf profile"
          },
          "path": ".var/app/io.gitlab.librewolf-community/.librewolf",
          "scope": "home",
          "default_selected": true,
          "size_hint": "medium"
        },
        {
          "id": "vivaldi_profile",
          "label": {
            "hu": "Vivaldi profil",
            "en": "Vivaldi profile"
          },
          "path": ".config/vivaldi",
          "scope": "home",
          "default_selected": true,
          "size_hint": "medium"
        },
        {
          "id": "brave_profile",
          "label": {
            "hu": "Brave Origin profil",
            "en": "Brave Origin profile"
          },
          "path": ".config/BraveSoftware/Brave-Origin",
          "scope": "home",
          "default_selected": true,
          "size_hint": "medium"
        },
        {
          "id": "bitwarden_config",
          "label": {
            "hu": "Bitwarden beállítások",
            "en": "Bitwarden settings"
          },
          "path": ".config/Bitwarden",
          "scope": "home",
          "default_selected": true,
          "size_hint": "small"
        },
        {
          "id": "heroic_config",
          "label": {
            "hu": "Heroic Games Launcher beállítások",
            "en": "Heroic Games Launcher settings"
          },
          "path": ".var/app/com.heroicgameslauncher.hgl/config/heroic",
          "scope": "home",
          "default_selected": true,
          "size_hint": "small"
        },
        {
          "id": "qbittorrent_config",
          "label": {
            "hu": "qBittorrent beállítások",
            "en": "qBittorrent settings"
          },
          "path": ".config/qBittorrent",
          "scope": "home",
          "default_selected": true,
          "size_hint": "small"
        },
        {
          "id": "signal_config",
          "label": {
            "hu": "Signal profil",
            "en": "Signal profile"
          },
          "path": ".config/Signal",
          "scope": "home",
          "default_selected": true,
          "size_hint": "small"
        },
        {
          "id": "telegram_data",
          "label": {
            "hu": "Telegram Desktop adatok",
            "en": "Telegram Desktop data"
          },
          "path": ".local/share/TelegramDesktop",
          "scope": "home",
          "default_selected": true,
          "size_hint": "medium"
        },
        {
          "id": "discord_config",
          "label": {
            "hu": "Discord beállítások",
            "en": "Discord settings"
          },
          "path": ".config/discord",
          "scope": "home",
          "default_selected": false,
          "size_hint": "small"
        },
        {
          "id": "vencord_config",
          "label": {
            "hu": "Vencord beállítások",
            "en": "Vencord settings"
          },
          "path": ".config/Vencord",
          "scope": "home",
          "default_selected": false,
          "size_hint": "small"
        },
        {
          "id": "steam_userdata",
          "label": {
            "hu": "Steam felhasználói adatok",
            "en": "Steam user data"
          },
          "path": ".local/share/Steam",
          "scope": "home",
          "default_selected": false,
          "size_hint": "large",
          "note": {
            "hu": "Nagy lehet, játékadatokat és cache-t is tartalmazhat.",
            "en": "Can be large, may include game data and cache."
          }
        },
        {
          "id": "lutris_data",
          "label": {
            "hu": "Lutris adatok",
            "en": "Lutris data"
          },
          "path": ".local/share/lutris",
          "scope": "home",
          "default_selected": false,
          "size_hint": "medium"
        }
      ]
    },
    {
      "id": "desktop",
      "label": {
        "hu": "Desktop és felület",
        "en": "Desktop and interface"
      },
      "description": {
        "hu": "Témák, GNOME shell kiegészítők és HUD/overlay beállítások.",
        "en": "Themes, GNOME Shell extensions, and HUD/overlay settings."
      },
      "default_expanded": true,
      "items": [
        {
          "id": "icons_dir",
          "label": {
            "hu": "Ikonok",
            "en": "Icons"
          },
          "path": ".icons",
          "scope": "home",
          "default_selected": true,
          "size_hint": "medium"
        },
        {
          "id": "themes_dir",
          "label": {
            "hu": "Témák",
            "en": "Themes"
          },
          "path": ".themes",
          "scope": "home",
          "default_selected": true,
          "size_hint": "medium"
        },
        {
          "id": "gnome_shell_data",
          "label": {
            "hu": "GNOME Shell kiegészítők",
            "en": "GNOME Shell extensions"
          },
          "path": ".local/share/gnome-shell",
          "scope": "home",
          "default_selected": true,
          "size_hint": "small"
        },
        {
          "id": "flatpak_overrides",
          "label": {
            "hu": "Flatpak override-ok",
            "en": "Flatpak overrides"
          },
          "path": ".local/share/flatpak/overrides",
          "scope": "home",
          "default_selected": true,
          "size_hint": "small"
        },
        {
          "id": "mangohud_config",
          "label": {
            "hu": "MangoHud beállítások",
            "en": "MangoHud settings"
          },
          "path": ".config/MangoHud",
          "scope": "home",
          "default_selected": true,
          "size_hint": "small"
        },
        {
          "id": "goverlay_config",
          "label": {
            "hu": "GOverlay beállítások",
            "en": "GOverlay settings"
          },
          "path": ".config/goverlay",
          "scope": "home",
          "default_selected": true,
          "size_hint": "small"
        }
      ]
    },
    {
      "id": "work",
      "label": {
        "hu": "Munka és produktivitás",
        "en": "Work and productivity"
      },
      "description": {
        "hu": "Irodai, média- és alkotó appok fontos user-adatkönyvtárai.",
        "en": "Important user data directories of office, media, and creative apps."
      },
      "default_expanded": false,
      "items": [
        {
          "id": "libreoffice_config",
          "label": {
            "hu": "LibreOffice beállítások",
            "en": "LibreOffice settings"
          },
          "path": ".config/libreoffice",
          "scope": "home",
          "default_selected": true,
          "size_hint": "small"
        },
        {
          "id": "onlyoffice_data",
          "label": {
            "hu": "OnlyOffice adatok",
            "en": "OnlyOffice data"
          },
          "path": ".local/share/onlyoffice",
          "scope": "home",
          "default_selected": false,
          "size_hint": "small"
        },
        {
          "id": "calibre_config",
          "label": {
            "hu": "Calibre beállítások",
            "en": "Calibre settings"
          },
          "path": ".config/calibre",
          "scope": "home",
          "default_selected": false,
          "size_hint": "small"
        },
        {
          "id": "kdenlive_data",
          "label": {
            "hu": "Kdenlive adatok",
            "en": "Kdenlive data"
          },
          "path": ".local/share/kdenlive",
          "scope": "home",
          "default_selected": false,
          "size_hint": "medium"
        },
        {
          "id": "freetube_config",
          "label": {
            "hu": "FreeTube profil",
            "en": "FreeTube profile"
          },
          "path": ".config/FreeTube",
          "scope": "home",
          "default_selected": false,
          "size_hint": "small"
        }
      ]
    },
    {
      "id": "content",
      "label": {
        "hu": "Nagy felhasználói tartalmak",
        "en": "Large user content"
      },
      "description": {
        "hu": "Nem alapból kijelölt könyvtárak, mert nagyok lehetnek.",
        "en": "Directories not selected by default because they can be large."
      },
      "default_expanded": false,
      "items": [
        {
          "id": "games_dir",
          "label": {
            "hu": "Games könyvtár",
            "en": "Games directory"
          },
          "path": "Games",
          "scope": "home",
          "default_selected": false,
          "size_hint": "xlarge",
          "note": {
            "hu": "Játékadatok miatt nagyon nagy lehet.",
            "en": "Can be very large due to game data."
          }
        },
        {
          "id": "calibre_library",
          "label": {
            "hu": "Calibre Library",
            "en": "Calibre Library"
          },
          "path": "Calibre Library",
          "scope": "home",
          "default_selected": false,
          "size_hint": "large"
        },
        {
          "id": "desktop_dir",
          "label": {
            "hu": "Asztal / Desktop",
            "en": "Desktop"
          },
          "path": "Desktop",
          "scope": "home",
          "default_selected": false,
          "size_hint": "medium"
        },
        {
          "id": "documents_dir",
          "label": {
            "hu": "Dokumentumok / Documents",
            "en": "Documents"
          },
          "path": "Documents",
          "scope": "home",
          "default_selected": false,
          "size_hint": "large"
        },
        {
          "id": "downloads_dir",
          "label": {
            "hu": "Letöltések / Downloads",
            "en": "Downloads"
          },
          "path": "Downloads",
          "scope": "home",
          "default_selected": false,
          "size_hint": "large"
        },
        {
          "id": "pictures_dir",
          "label": {
            "hu": "Képek / Pictures",
            "en": "Pictures"
          },
          "path": "Pictures",
          "scope": "home",
          "default_selected": false,
          "size_hint": "large"
        },
        {
          "id": "videos_dir",
          "label": {
            "hu": "Videók / Videos",
            "en": "Videos"
          },
          "path": "Videos",
          "scope": "home",
          "default_selected": false,
          "size_hint": "large"
        },
        {
          "id": "music_dir",
          "label": {
            "hu": "Zenék / Music",
            "en": "Music"
          },
          "path": "Music",
          "scope": "home",
          "default_selected": false,
          "size_hint": "large"
        }
      ]
    },
    {
      "id": "system",
      "label": {
        "hu": "Rendszerközeli mentés",
        "en": "System-level backup"
      },
      "description": {
        "hu": "Csak haladó felhasználóknak, külön megerősítéssel.",
        "en": "For advanced users only, requires extra confirmation."
      },
      "default_expanded": false,
      "items": [
        {
          "id": "libvirt_system",
          "label": {
            "hu": "libvirt rendszerbeállítások",
            "en": "libvirt system configuration"
          },
          "path": "/etc/libvirt",
          "scope": "system",
          "default_selected": false,
          "size_hint": "small",
          "requires_root": true
        },
        {
          "id": "jellyfin_web_config",
          "label": {
            "hu": "Jellyfin web config",
            "en": "Jellyfin web config"
          },
          "path": "/usr/share/jellyfin/web/config.json",
          "scope": "system",
          "default_selected": false,
          "size_hint": "small",
          "requires_root": true
        }
      ]
    }
  ]
}
